examples/__init__.py
examples/custom_exploration_scheduler.py
examples/custom_policy.py
mighty/__init__.py
mighty/run_mighty.py
mighty/mighty_agents/__init__.py
mighty/mighty_agents/base_agent.py
mighty/mighty_agents/dqn.py
mighty/mighty_agents/factory.py
mighty/mighty_agents/ppo.py
mighty/mighty_agents/sac.py
mighty/mighty_exploration/__init__.py
mighty/mighty_exploration/decaying_epsilon_greedy.py
mighty/mighty_exploration/epsilon_greedy.py
mighty/mighty_exploration/ez_greedy.py
mighty/mighty_exploration/mighty_exploration_policy.py
mighty/mighty_exploration/stochastic_policy.py
mighty/mighty_meta/__init__.py
mighty/mighty_meta/cosine_lr_schedule.py
mighty/mighty_meta/mighty_component.py
mighty/mighty_meta/plr.py
mighty/mighty_meta/rnd.py
mighty/mighty_meta/space.py
mighty/mighty_models/__init__.py
mighty/mighty_models/dqn.py
mighty/mighty_models/networks.py
mighty/mighty_models/ppo.py
mighty/mighty_models/sac.py
mighty/mighty_replay/__init__.py
mighty/mighty_replay/buffer.py
mighty/mighty_replay/mighty_prioritized_replay.py
mighty/mighty_replay/mighty_replay_buffer.py
mighty/mighty_replay/mighty_rollout_buffer.py
mighty/mighty_runners/__init__.py
mighty/mighty_runners/factory.py
mighty/mighty_runners/mighty_es_runner.py
mighty/mighty_runners/mighty_online_runner.py
mighty/mighty_runners/mighty_runner.py
mighty/mighty_update/__init__.py
mighty/mighty_update/ppo_update.py
mighty/mighty_update/q_learning.py
mighty/mighty_update/sac_update.py
mighty/mighty_utils/__init__.py
mighty/mighty_utils/envs.py
mighty/mighty_utils/mighty_types.py
mighty/mighty_utils/plotting.py
mighty/mighty_utils/test_helpers.py
mighty/mighty_utils/update_utils.py
mighty/mighty_utils/wrappers.py
mighty_rl-1.0.0.dist-info/licenses/LICENSE
mighty_rl-1.0.0.dist-info/METADATA
mighty_rl-1.0.0.dist-info/WHEEL
mighty_rl-1.0.0.dist-info/top_level.txt
mighty_rl-1.0.0.dist-info/RECORD
