Metadata-Version: 2.4
Name: Mighty-RL
Version: 1.0.0
Summary: A modular, meta-learning-ready RL library.
Author-email: "AutoRL@LUHAI" <a.mohan@ai.uni-hannover.de>
License: 
Keywords: Reinforcement Learning,MetaRL,Generalization in RL
Classifier: Intended Audience :: Developers
Classifier: Programming Language :: Python :: 3 :: Only
Classifier: Development Status :: 3 - Alpha
Classifier: Topic :: Utilities
Classifier: Topic :: Scientific/Engineering
Classifier: Topic :: Scientific/Engineering :: Artificial Intelligence
Classifier: License :: OSI Approved :: BSD License
Requires-Python: <3.12,>=3.11
License-File: LICENSE
Requires-Dist: numpy<2
Requires-Dist: gymnasium
Requires-Dist: matplotlib~=3.4
Requires-Dist: seaborn~=0.11
Requires-Dist: tensorboard
Requires-Dist: hydra-core~=1.2
Requires-Dist: hydra-colorlog~=1.2
Requires-Dist: hydra-submitit-launcher~=1.2
Requires-Dist: pandas
Requires-Dist: scipy
Requires-Dist: rich~=12.4
Requires-Dist: wandb~=0.12
Requires-Dist: torch~=2.7
Requires-Dist: dill
Requires-Dist: imageio
Requires-Dist: evosax==0.1.6
Requires-Dist: rliable
Requires-Dist: seaborn
Requires-Dist: uniplot
Requires-Dist: jax~=0.7
Requires-Dist: flax~=0.11
Provides-Extra: dev
Requires-Dist: ruff; extra == "dev"
Requires-Dist: mypy; extra == "dev"
Requires-Dist: build; extra == "dev"
Requires-Dist: pytest; extra == "dev"
Requires-Dist: pytest-cov; extra == "dev"
Provides-Extra: carl
Requires-Dist: carl_bench[brax]==1.1.1; extra == "carl"
Provides-Extra: dacbench
Requires-Dist: dacbench==0.4.0; extra == "dacbench"
Requires-Dist: torchvision; extra == "dacbench"
Provides-Extra: pufferlib
Requires-Dist: pufferlib==2.0.6; extra == "pufferlib"
Provides-Extra: docs
Requires-Dist: mkdocs; extra == "docs"
Requires-Dist: mkdocs-material; extra == "docs"
Requires-Dist: mkdocs-autorefs; extra == "docs"
Requires-Dist: mkdocs-gen-files; extra == "docs"
Requires-Dist: mkdocs-literate-nav; extra == "docs"
Requires-Dist: mkdocs-glightbox; extra == "docs"
Requires-Dist: mkdocs-glossary-plugin; extra == "docs"
Requires-Dist: mkdocstrings[python]; extra == "docs"
Requires-Dist: markdown-exec[ansi]; extra == "docs"
Requires-Dist: mike; extra == "docs"
Requires-Dist: mkdocs-mermaid2-plugin; extra == "docs"
Provides-Extra: examples
Dynamic: license-file
